{
  "setting": {
    "date": {
      "year": 2016,
      "month": 4,
      "day": 7
    }
  },
  "home_team": {
    "team_id": 147,
    "batting_stats": {
      "games_played": 3,
      "ground_outs": 24,
      "air_outs": 28,
      "runs": 27,
      "doubles": 5,
      "triples": 1,
      "home_runs": 7,
      "strike_outs": 21,
      "base_on_balls": 12,
      "intentional_walks": 0,
      "hits": 33,
      "hit_by_pitch": 0,
      "avg": 0.314,
      "at_bats": 105,
      "obp": 0.381,
      "slg": 0.581,
      "ops": 0.962,
      "caught_stealing": 0,
      "stolen_bases": 4,
      "stolen_base_percentage": 1.0,
      "ground_into_double_play": 2,
      "number_of_pitches": 508,
      "plate_appearances": 119,
      "total_bases": 61,
      "rbi": 27,
      "left_on_base": 17,
      "sac_bunts": 0,
      "sac_flies": 1,
      "babip": 0.333,
      "ground_outs_to_airouts": 0.86,
      "at_bats_per_home_run": 15.0
    },
    "pitching_stats": {
      "games_played": 3,
      "games_started": 3,
      "ground_outs": 28,
      "air_outs": 19,
      "runs": 16,
      "doubles": 7,
      "triples": 0,
      "home_runs": 6,
      "strike_outs": 34,
      "base_on_balls": 4,
      "intentional_walks": 0,
      "hits": 27,
      "hit_by_pitch": 2,
      "avg": 0.25,
      "at_bats": 108,
      "era": 4.33,
      "innings_pitched": 27.0,
      "wins": 2,
      "losses": 1,
      "ties": 0,
      "saves": 2,
      "save_opportunities": 2,
      "holds": 1,
      "blown_saves": 0,
      "earned_runs": 13,
      "whip": 1.15,
      "batters_faced": 114,
      "outs": 81,
      "games_pitched": 3,
      "complete_games": 0,
      "shutouts": 0,
      "strikes": 295,
      "strike_percentage": 0.65,
      "hit_batsmen": 2,
      "balks": 0,
      "wild_pitches": 1,
      "pickoffs": 0,
      "ground_outs_to_airouts": 1.47,
      "win_percentage": 0.667,
      "pitches_per_inning": 16.93,
      "games_finished": 3,
      "strikeout_walk_ratio": 8.5,
      "strikeouts_per_9inn": 11.33,
      "walks_per_9inn": 1.33,
      "hits_per_9inn": 9.0,
      "runs_scored_per_9": 5.33,
      "home_runs_per_9": 2.0,
      "sac_bunts": 0,
      "sac_flies": 0
    },
    "fielding_stats": {
      "games_played": 3,
      "games_started": 3,
      "assists": 28,
      "put_outs": 81,
      "errors": 1,
      "chances": 110,
      "fielding": 0.991,
      "range_factor_per_game": 36.33,
      "range_factor_per_9inn": 36.33,
      "innings": 27.0,
      "games": 3,
      "double_plays": 1,
      "triple_plays": 0,
      "throwing_errors": 1
    }
  },
  "away_team": {
    "team_id": 117,
    "batting_stats": {
      "games_played": 3,
      "ground_outs": 28,
      "air_outs": 19,
      "runs": 16,
      "doubles": 7,
      "triples": 0,
      "home_runs": 6,
      "strike_outs": 34,
      "base_on_balls": 4,
      "intentional_walks": 0,
      "hits": 27,
      "hit_by_pitch": 2,
      "avg": 0.25,
      "at_bats": 108,
      "obp": 0.289,
      "slg": 0.481,
      "ops": 0.77,
      "caught_stealing": 0,
      "stolen_bases": 3,
      "stolen_base_percentage": 1.0,
      "ground_into_double_play": 1,
      "number_of_pitches": 457,
      "plate_appearances": 114,
      "total_bases": 52,
      "rbi": 15,
      "left_on_base": 17,
      "sac_bunts": 0,
      "sac_flies": 0,
      "babip": 0.309,
      "ground_outs_to_airouts": 1.47,
      "at_bats_per_home_run": 18.0
    },
    "pitching_stats": {
      "games_played": 3,
      "games_started": 3,
      "ground_outs": 24,
      "air_outs": 28,
      "runs": 27,
      "doubles": 5,
      "triples": 1,
      "home_runs": 7,
      "strike_outs": 21,
      "base_on_balls": 12,
      "intentional_walks": 0,
      "hits": 33,
      "hit_by_pitch": 0,
      "avg": 0.314,
      "at_bats": 105,
      "era": 9.36,
      "innings_pitched": 25.0,
      "wins": 1,
      "losses": 2,
      "ties": 0,
      "saves": 1,
      "save_opportunities": 1,
      "holds": 1,
      "blown_saves": 0,
      "earned_runs": 26,
      "whip": 1.8,
      "batters_faced": 119,
      "outs": 75,
      "games_pitched": 3,
      "complete_games": 0,
      "shutouts": 0,
      "strikes": 308,
      "strike_percentage": 0.61,
      "hit_batsmen": 0,
      "balks": 0,
      "wild_pitches": 0,
      "pickoffs": 0,
      "ground_outs_to_airouts": 0.86,
      "win_percentage": 0.333,
      "pitches_per_inning": 20.32,
      "games_finished": 3,
      "strikeout_walk_ratio": 1.75,
      "strikeouts_per_9inn": 7.56,
      "walks_per_9inn": 4.32,
      "hits_per_9inn": 11.88,
      "runs_scored_per_9": 9.72,
      "home_runs_per_9": 2.52,
      "sac_bunts": 0,
      "sac_flies": 1
    },
    "fielding_stats": {
      "games_played": 3,
      "games_started": 3,
      "assists": 21,
      "put_outs": 75,
      "errors": 2,
      "chances": 98,
      "fielding": 0.98,
      "range_factor_per_game": 32.0,
      "range_factor_per_9inn": 34.56,
      "innings": 25.0,
      "games": 3,
      "double_plays": 2,
      "triple_plays": 0,
      "throwing_errors": 0
    }
  },
  "result": {
    "home_team_score": 8,
    "away_team_score": 5
  }
}