{
  "setting": {
    "date": {
      "year": 2018,
      "month": 9,
      "day": 12
    }
  },
  "home_team": {
    "team_id": 116,
    "batting_stats": {
      "games_played": 28,
      "ground_outs": 232,
      "air_outs": 232,
      "runs": 127,
      "doubles": 54,
      "triples": 3,
      "home_runs": 32,
      "strike_outs": 4,
      "base_on_balls": 85,
      "intentional_walks": 4,
      "hits": 246,
      "hit_by_pitch": 10,
      "avg": 0.257,
      "at_bats": 959,
      "obp": 0.321,
      "slg": 0.419,
      "ops": 0.74,
      "caught_stealing": 1,
      "stolen_bases": 9,
      "stolen_base_percentage": 0.9,
      "ground_into_double_play": 21,
      "number_of_pitches": 4233,
      "plate_appearances": 1065,
      "total_bases": 402,
      "rbi": 120,
      "left_on_base": 195,
      "sac_bunts": 4,
      "sac_flies": 7,
      "babip": 0.318,
      "ground_outs_to_airouts": 1.0,
      "at_bats_per_home_run": 29.97
    },
    "pitching_stats": {
      "games_played": 28,
      "games_started": 28,
      "ground_outs": 210,
      "air_outs": 27,
      "runs": 148,
      "doubles": 41,
      "triples": 3,
      "home_runs": 47,
      "strike_outs": 225,
      "base_on_balls": 81,
      "intentional_walks": 3,
      "hits": 233,
      "hit_by_pitch": 12,
      "avg": 0.249,
      "at_bats": 934,
      "era": 4.76,
      "innings_pitched": 244.0,
      "wins": 10,
      "losses": 18,
      "ties": 0,
      "saves": 3,
      "save_opportunities": 8,
      "holds": 12,
      "blown_saves": 5,
      "earned_runs": 129,
      "whip": 1.29,
      "batters_faced": 1044,
      "outs": 732,
      "games_pitched": 28,
      "complete_games": 0,
      "shutouts": 0,
      "strikes": 2621,
      "strike_percentage": 0.64,
      "hit_batsmen": 12,
      "balks": 1,
      "wild_pitches": 7,
      "pickoffs": 3,
      "ground_outs_to_airouts": 0.74,
      "win_percentage": 0.357,
      "pitches_per_inning": 16.72,
      "games_finished": 28,
      "strikeout_walk_ratio": 2.78,
      "strikeouts_per_9inn": 8.3,
      "walks_per_9inn": 2.99,
      "hits_per_9inn": 8.59,
      "runs_scored_per_9": 5.46,
      "home_runs_per_9": 1.73,
      "sac_bunts": 1,
      "sac_flies": 16
    },
    "fielding_stats": {
      "games_played": 28,
      "games_started": 28,
      "assists": 226,
      "put_outs": 732,
      "errors": 20,
      "chances": 978,
      "fielding": 0.98,
      "range_factor_per_game": 34.21,
      "range_factor_per_9inn": 35.34,
      "innings": 244.0,
      "games": 28,
      "double_plays": 15,
      "triple_plays": 0,
      "throwing_errors": 10
    }
  },
  "away_team": {
    "team_id": 117,
    "batting_stats": {
      "games_played": 27,
      "ground_outs": 218,
      "air_outs": 12,
      "runs": 142,
      "doubles": 46,
      "triples": 4,
      "home_runs": 40,
      "strike_outs": 188,
      "base_on_balls": 91,
      "intentional_walks": 3,
      "hits": 232,
      "hit_by_pitch": 8,
      "avg": 0.259,
      "at_bats": 897,
      "obp": 0.329,
      "slg": 0.453,
      "ops": 0.782,
      "caught_stealing": 4,
      "stolen_bases": 5,
      "stolen_base_percentage": 0.556,
      "ground_into_double_play": 32,
      "number_of_pitches": 3921,
      "plate_appearances": 1007,
      "total_bases": 406,
      "rbi": 133,
      "left_on_base": 156,
      "sac_bunts": 0,
      "sac_flies": 9,
      "babip": 0.283,
      "ground_outs_to_airouts": 0.81,
      "at_bats_per_home_run": 22.42
    },
    "pitching_stats": {
      "games_played": 27,
      "games_started": 27,
      "ground_outs": 208,
      "air_outs": 217,
      "runs": 95,
      "doubles": 42,
      "triples": 3,
      "home_runs": 24,
      "strike_outs": 26,
      "base_on_balls": 84,
      "intentional_walks": 1,
      "hits": 210,
      "hit_by_pitch": 12,
      "avg": 0.231,
      "at_bats": 910,
      "era": 3.33,
      "innings_pitched": 240.2,
      "wins": 19,
      "losses": 8,
      "ties": 0,
      "saves": 11,
      "save_opportunities": 15,
      "holds": 31,
      "blown_saves": 4,
      "earned_runs": 89,
      "whip": 1.22,
      "batters_faced": 1013,
      "outs": 722,
      "games_pitched": 27,
      "complete_games": 0,
      "shutouts": 0,
      "strikes": 2573,
      "strike_percentage": 0.65,
      "hit_batsmen": 12,
      "balks": 1,
      "wild_pitches": 16,
      "pickoffs": 2,
      "ground_outs_to_airouts": 0.96,
      "win_percentage": 0.704,
      "pitches_per_inning": 16.52,
      "games_finished": 27,
      "strikeout_walk_ratio": 3.36,
      "strikeouts_per_9inn": 10.55,
      "walks_per_9inn": 3.14,
      "hits_per_9inn": 7.85,
      "runs_scored_per_9": 3.55,
      "home_runs_per_9": 0.9,
      "sac_bunts": 0,
      "sac_flies": 7
    },
    "fielding_stats": {
      "games_played": 27,
      "games_started": 27,
      "assists": 219,
      "put_outs": 722,
      "errors": 8,
      "chances": 949,
      "fielding": 0.992,
      "range_factor_per_game": 34.85,
      "range_factor_per_9inn": 35.29,
      "innings": 240.2,
      "games": 27,
      "double_plays": 18,
      "triple_plays": 0,
      "throwing_errors": 6
    }
  },
  "result": {
    "home_team_score": 4,
    "away_team_score": 5
  }
}