{
  "setting": {
    "date": {
      "year": 2016,
      "month": 6,
      "day": 17
    }
  },
  "home_team": {
    "team_id": 118,
    "batting_stats": {
      "games_played": 29,
      "ground_outs": 8,
      "air_outs": 226,
      "runs": 125,
      "doubles": 50,
      "triples": 5,
      "home_runs": 26,
      "strike_outs": 228,
      "base_on_balls": 64,
      "intentional_walks": 6,
      "hits": 34,
      "hit_by_pitch": 6,
      "avg": 0.293,
      "at_bats": 989,
      "obp": 0.337,
      "slg": 0.433,
      "ops": 0.77,
      "caught_stealing": 7,
      "stolen_bases": 16,
      "stolen_base_percentage": 0.696,
      "ground_into_double_play": 24,
      "number_of_pitches": 4060,
      "plate_appearances": 1078,
      "total_bases": 428,
      "rbi": 118,
      "left_on_base": 201,
      "sac_bunts": 10,
      "sac_flies": 9,
      "babip": 0.355,
      "ground_outs_to_airouts": 1.17,
      "at_bats_per_home_run": 38.04
    },
    "pitching_stats": {
      "games_played": 29,
      "games_started": 29,
      "ground_outs": 250,
      "air_outs": 240,
      "runs": 124,
      "doubles": 37,
      "triples": 3,
      "home_runs": 47,
      "strike_outs": 234,
      "base_on_balls": 81,
      "intentional_walks": 1,
      "hits": 250,
      "hit_by_pitch": 13,
      "avg": 0.26,
      "at_bats": 962,
      "era": 4.15,
      "innings_pitched": 251.2,
      "wins": 17,
      "losses": 12,
      "ties": 0,
      "saves": 10,
      "save_opportunities": 13,
      "holds": 21,
      "blown_saves": 3,
      "earned_runs": 116,
      "whip": 1.32,
      "batters_faced": 1068,
      "outs": 755,
      "games_pitched": 29,
      "complete_games": 0,
      "shutouts": 0,
      "strikes": 2666,
      "strike_percentage": 0.65,
      "hit_batsmen": 13,
      "balks": 0,
      "wild_pitches": 10,
      "pickoffs": 2,
      "ground_outs_to_airouts": 1.04,
      "win_percentage": 0.586,
      "pitches_per_inning": 16.19,
      "games_finished": 29,
      "strikeout_walk_ratio": 2.89,
      "strikeouts_per_9inn": 8.37,
      "walks_per_9inn": 2.9,
      "hits_per_9inn": 8.94,
      "runs_scored_per_9": 4.43,
      "home_runs_per_9": 1.68,
      "sac_bunts": 5,
      "sac_flies": 7
    },
    "fielding_stats": {
      "games_played": 29,
      "games_started": 29,
      "assists": 274,
      "put_outs": 755,
      "errors": 20,
      "chances": 1049,
      "fielding": 0.981,
      "range_factor_per_game": 35.48,
      "range_factor_per_9inn": 36.9,
      "innings": 251.2,
      "games": 29,
      "double_plays": 29,
      "triple_plays": 0,
      "throwing_errors": 9
    }
  },
  "away_team": {
    "team_id": 116,
    "batting_stats": {
      "games_played": 28,
      "ground_outs": 249,
      "air_outs": 234,
      "runs": 148,
      "doubles": 49,
      "triples": 9,
      "home_runs": 38,
      "strike_outs": 226,
      "base_on_balls": 87,
      "intentional_walks": 9,
      "hits": 26,
      "hit_by_pitch": 5,
      "avg": 0.288,
      "at_bats": 978,
      "obp": 0.347,
      "slg": 0.473,
      "ops": 0.82,
      "caught_stealing": 8,
      "stolen_bases": 14,
      "stolen_base_percentage": 0.636,
      "ground_into_double_play": 22,
      "number_of_pitches": 4205,
      "plate_appearances": 1083,
      "total_bases": 463,
      "rbi": 142,
      "left_on_base": 197,
      "sac_bunts": 6,
      "sac_flies": 7,
      "babip": 0.338,
      "ground_outs_to_airouts": 1.06,
      "at_bats_per_home_run": 25.74
    },
    "pitching_stats": {
      "games_played": 28,
      "games_started": 28,
      "ground_outs": 7,
      "air_outs": 243,
      "runs": 130,
      "doubles": 46,
      "triples": 14,
      "home_runs": 27,
      "strike_outs": 211,
      "base_on_balls": 85,
      "intentional_walks": 7,
      "hits": 239,
      "hit_by_pitch": 9,
      "avg": 0.254,
      "at_bats": 940,
      "era": 4.35,
      "innings_pitched": 248.1,
      "wins": 16,
      "losses": 12,
      "ties": 0,
      "saves": 9,
      "save_opportunities": 11,
      "holds": 10,
      "blown_saves": 2,
      "earned_runs": 120,
      "whip": 1.3,
      "batters_faced": 1050,
      "outs": 745,
      "games_pitched": 28,
      "complete_games": 0,
      "shutouts": 2,
      "strikes": 2559,
      "strike_percentage": 0.64,
      "hit_batsmen": 9,
      "balks": 0,
      "wild_pitches": 9,
      "pickoffs": 0,
      "ground_outs_to_airouts": 1.08,
      "win_percentage": 0.571,
      "pitches_per_inning": 16.04,
      "games_finished": 28,
      "strikeout_walk_ratio": 2.48,
      "strikeouts_per_9inn": 7.65,
      "walks_per_9inn": 3.08,
      "hits_per_9inn": 8.66,
      "runs_scored_per_9": 4.71,
      "home_runs_per_9": 0.98,
      "sac_bunts": 3,
      "sac_flies": 13
    },
    "fielding_stats": {
      "games_played": 28,
      "games_started": 28,
      "assists": 287,
      "put_outs": 745,
      "errors": 12,
      "chances": 1044,
      "fielding": 0.989,
      "range_factor_per_game": 36.86,
      "range_factor_per_9inn": 37.45,
      "innings": 248.1,
      "games": 28,
      "double_plays": 22,
      "triple_plays": 0,
      "throwing_errors": 5
    }
  },
  "result": {
    "home_team_score": 10,
    "away_team_score": 3
  }
}