{
  "setting": {
    "date": {
      "year": 2021,
      "month": 4,
      "day": 10
    }
  },
  "home_team": {
    "team_id": 117,
    "batting_stats": {
      "games_played": 9,
      "ground_outs": 81,
      "air_outs": 84,
      "runs": 56,
      "doubles": 20,
      "triples": 1,
      "home_runs": 16,
      "strike_outs": 70,
      "base_on_balls": 29,
      "intentional_walks": 1,
      "hits": 90,
      "hit_by_pitch": 5,
      "avg": 0.28,
      "at_bats": 321,
      "obp": 0.345,
      "slg": 0.498,
      "ops": 0.843,
      "caught_stealing": 1,
      "stolen_bases": 2,
      "stolen_base_percentage": 0.667,
      "ground_into_double_play": 9,
      "number_of_pitches": 1430,
      "plate_appearances": 359,
      "total_bases": 160,
      "rbi": 52,
      "left_on_base": 63,
      "sac_bunts": 0,
      "sac_flies": 4,
      "babip": 0.31,
      "ground_outs_to_airouts": 0.96,
      "at_bats_per_home_run": 20.06
    },
    "pitching_stats": {
      "games_played": 9,
      "games_started": 9,
      "ground_outs": 73,
      "air_outs": 87,
      "runs": 33,
      "doubles": 8,
      "triples": 2,
      "home_runs": 8,
      "strike_outs": 74,
      "base_on_balls": 29,
      "intentional_walks": 1,
      "hits": 62,
      "hit_by_pitch": 6,
      "avg": 0.212,
      "at_bats": 292,
      "era": 3.49,
      "innings_pitched": 80.0,
      "wins": 6,
      "losses": 3,
      "ties": 0,
      "saves": 1,
      "save_opportunities": 2,
      "holds": 7,
      "blown_saves": 1,
      "earned_runs": 31,
      "whip": 1.14,
      "batters_faced": 331,
      "outs": 240,
      "games_pitched": 9,
      "complete_games": 0,
      "shutouts": 0,
      "strikes": 861,
      "strike_percentage": 0.63,
      "hit_batsmen": 6,
      "balks": 0,
      "wild_pitches": 5,
      "pickoffs": 0,
      "ground_outs_to_airouts": 0.84,
      "win_percentage": 0.667,
      "pitches_per_inning": 17.11,
      "games_finished": 9,
      "strikeout_walk_ratio": 2.55,
      "strikeouts_per_9inn": 8.33,
      "walks_per_9inn": 3.26,
      "hits_per_9inn": 6.98,
      "runs_scored_per_9": 3.71,
      "home_runs_per_9": 0.9,
      "sac_bunts": 1,
      "sac_flies": 3
    },
    "fielding_stats": {
      "games_played": 9,
      "games_started": 9,
      "assists": 76,
      "put_outs": 240,
      "errors": 5,
      "chances": 321,
      "fielding": 0.984,
      "range_factor_per_game": 35.11,
      "range_factor_per_9inn": 35.55,
      "innings": 80.0,
      "games": 9,
      "double_plays": 8,
      "triple_plays": 0,
      "throwing_errors": 4
    }
  },
  "away_team": {
    "team_id": 133,
    "batting_stats": {
      "games_played": 10,
      "ground_outs": 87,
      "air_outs": 86,
      "runs": 32,
      "doubles": 10,
      "triples": 2,
      "home_runs": 8,
      "strike_outs": 94,
      "base_on_balls": 34,
      "intentional_walks": 0,
      "hits": 61,
      "hit_by_pitch": 7,
      "avg": 0.189,
      "at_bats": 323,
      "obp": 0.278,
      "slg": 0.307,
      "ops": 0.585,
      "caught_stealing": 1,
      "stolen_bases": 6,
      "stolen_base_percentage": 0.857,
      "ground_into_double_play": 5,
      "number_of_pitches": 1520,
      "plate_appearances": 369,
      "total_bases": 99,
      "rbi": 31,
      "left_on_base": 67,
      "sac_bunts": 2,
      "sac_flies": 3,
      "babip": 0.237,
      "ground_outs_to_airouts": 1.01,
      "at_bats_per_home_run": 40.38
    },
    "pitching_stats": {
      "games_played": 10,
      "games_started": 10,
      "ground_outs": 90,
      "air_outs": 99,
      "runs": 64,
      "doubles": 24,
      "triples": 1,
      "home_runs": 17,
      "strike_outs": 74,
      "base_on_balls": 39,
      "intentional_walks": 2,
      "hits": 105,
      "hit_by_pitch": 8,
      "avg": 0.289,
      "at_bats": 363,
      "era": 6.2,
      "innings_pitched": 90.0,
      "wins": 3,
      "losses": 7,
      "ties": 0,
      "saves": 0,
      "save_opportunities": 0,
      "holds": 1,
      "blown_saves": 0,
      "earned_runs": 62,
      "whip": 1.6,
      "batters_faced": 415,
      "outs": 270,
      "games_pitched": 10,
      "complete_games": 0,
      "shutouts": 0,
      "strikes": 1019,
      "strike_percentage": 0.63,
      "hit_batsmen": 8,
      "balks": 0,
      "wild_pitches": 7,
      "pickoffs": 0,
      "ground_outs_to_airouts": 0.91,
      "win_percentage": 0.3,
      "pitches_per_inning": 18.1,
      "games_finished": 10,
      "strikeout_walk_ratio": 1.9,
      "strikeouts_per_9inn": 7.4,
      "walks_per_9inn": 3.9,
      "hits_per_9inn": 10.5,
      "runs_scored_per_9": 6.4,
      "home_runs_per_9": 1.7,
      "sac_bunts": 0,
      "sac_flies": 5
    },
    "fielding_stats": {
      "games_played": 10,
      "games_started": 10,
      "assists": 90,
      "put_outs": 270,
      "errors": 4,
      "chances": 364,
      "fielding": 0.989,
      "range_factor_per_game": 36.0,
      "range_factor_per_9inn": 36.0,
      "innings": 90.0,
      "games": 10,
      "double_plays": 10,
      "triple_plays": 0,
      "throwing_errors": 1
    }
  },
  "result": {
    "home_team_score": 3,
    "away_team_score": 7
  }
}