{
  "setting": {
    "date": {
      "year": 2017,
      "month": 4,
      "day": 20
    }
  },
  "home_team": {
    "team_id": 135,
    "batting_stats": {
      "games_played": 17,
      "ground_outs": 148,
      "air_outs": 147,
      "runs": 52,
      "doubles": 19,
      "triples": 2,
      "home_runs": 20,
      "strike_outs": 135,
      "base_on_balls": 47,
      "intentional_walks": 1,
      "hits": 110,
      "hit_by_pitch": 6,
      "avg": 0.207,
      "at_bats": 531,
      "obp": 0.277,
      "slg": 0.363,
      "ops": 0.64,
      "caught_stealing": 5,
      "stolen_bases": 5,
      "stolen_base_percentage": 0.5,
      "ground_into_double_play": 18,
      "number_of_pitches": 2149,
      "plate_appearances": 593,
      "total_bases": 193,
      "rbi": 51,
      "left_on_base": 94,
      "sac_bunts": 5,
      "sac_flies": 4,
      "babip": 0.237,
      "ground_outs_to_airouts": 1.01,
      "at_bats_per_home_run": 26.55
    },
    "pitching_stats": {
      "games_played": 17,
      "games_started": 17,
      "ground_outs": 171,
      "air_outs": 131,
      "runs": 80,
      "doubles": 28,
      "triples": 1,
      "home_runs": 24,
      "strike_outs": 120,
      "base_on_balls": 60,
      "intentional_walks": 4,
      "hits": 131,
      "hit_by_pitch": 4,
      "avg": 0.238,
      "at_bats": 551,
      "era": 4.39,
      "innings_pitched": 145.2,
      "wins": 7,
      "losses": 10,
      "ties": 0,
      "saves": 4,
      "save_opportunities": 5,
      "holds": 4,
      "blown_saves": 1,
      "earned_runs": 71,
      "whip": 1.31,
      "batters_faced": 617,
      "outs": 437,
      "games_pitched": 17,
      "complete_games": 0,
      "shutouts": 3,
      "strikes": 1445,
      "strike_percentage": 0.62,
      "hit_batsmen": 4,
      "balks": 3,
      "wild_pitches": 7,
      "pickoffs": 1,
      "ground_outs_to_airouts": 1.31,
      "win_percentage": 0.412,
      "pitches_per_inning": 15.91,
      "games_finished": 17,
      "strikeout_walk_ratio": 2.0,
      "strikeouts_per_9inn": 7.41,
      "walks_per_9inn": 3.71,
      "hits_per_9inn": 8.09,
      "runs_scored_per_9": 4.94,
      "home_runs_per_9": 1.48,
      "sac_bunts": 0,
      "sac_flies": 2
    },
    "fielding_stats": {
      "games_played": 17,
      "games_started": 17,
      "assists": 177,
      "put_outs": 437,
      "errors": 13,
      "chances": 627,
      "fielding": 0.979,
      "range_factor_per_game": 36.12,
      "range_factor_per_9inn": 38.11,
      "innings": 145.2,
      "games": 17,
      "double_plays": 18,
      "triple_plays": 0,
      "throwing_errors": 10
    }
  },
  "away_team": {
    "team_id": 109,
    "batting_stats": {
      "games_played": 17,
      "ground_outs": 142,
      "air_outs": 133,
      "runs": 79,
      "doubles": 26,
      "triples": 7,
      "home_runs": 14,
      "strike_outs": 162,
      "base_on_balls": 50,
      "intentional_walks": 2,
      "hits": 148,
      "hit_by_pitch": 3,
      "avg": 0.254,
      "at_bats": 582,
      "obp": 0.316,
      "slg": 0.395,
      "ops": 0.711,
      "caught_stealing": 6,
      "stolen_bases": 16,
      "stolen_base_percentage": 0.727,
      "ground_into_double_play": 8,
      "number_of_pitches": 2444,
      "plate_appearances": 638,
      "total_bases": 230,
      "rbi": 73,
      "left_on_base": 116,
      "sac_bunts": 1,
      "sac_flies": 2,
      "babip": 0.328,
      "ground_outs_to_airouts": 1.07,
      "at_bats_per_home_run": 41.57
    },
    "pitching_stats": {
      "games_played": 17,
      "games_started": 17,
      "ground_outs": 158,
      "air_outs": 144,
      "runs": 67,
      "doubles": 34,
      "triples": 4,
      "home_runs": 13,
      "strike_outs": 138,
      "base_on_balls": 56,
      "intentional_walks": 2,
      "hits": 136,
      "hit_by_pitch": 4,
      "avg": 0.242,
      "at_bats": 563,
      "era": 3.55,
      "innings_pitched": 147.0,
      "wins": 10,
      "losses": 7,
      "ties": 0,
      "saves": 5,
      "save_opportunities": 5,
      "holds": 10,
      "blown_saves": 0,
      "earned_runs": 58,
      "whip": 1.31,
      "batters_faced": 636,
      "outs": 441,
      "games_pitched": 17,
      "complete_games": 1,
      "shutouts": 0,
      "strikes": 1525,
      "strike_percentage": 0.62,
      "hit_batsmen": 4,
      "balks": 2,
      "wild_pitches": 9,
      "pickoffs": 3,
      "ground_outs_to_airouts": 1.1,
      "win_percentage": 0.588,
      "pitches_per_inning": 16.86,
      "games_finished": 16,
      "strikeout_walk_ratio": 2.46,
      "strikeouts_per_9inn": 8.45,
      "walks_per_9inn": 3.43,
      "hits_per_9inn": 8.33,
      "runs_scored_per_9": 4.1,
      "home_runs_per_9": 0.8,
      "sac_bunts": 4,
      "sac_flies": 9
    },
    "fielding_stats": {
      "games_played": 17,
      "games_started": 17,
      "assists": 151,
      "put_outs": 441,
      "errors": 16,
      "chances": 608,
      "fielding": 0.974,
      "range_factor_per_game": 34.82,
      "range_factor_per_9inn": 36.24,
      "innings": 147.0,
      "games": 17,
      "double_plays": 8,
      "triple_plays": 0,
      "throwing_errors": 9
    }
  },
  "result": {
    "home_team_score": 4,
    "away_team_score": 1
  }
}