{
  "setting": {
    "date": {
      "year": 2020,
      "month": 9,
      "day": 6
    }
  },
  "home_team": {
    "team_id": 134,
    "batting_stats": {
      "games_played": 26,
      "ground_outs": 232,
      "air_outs": 206,
      "runs": 109,
      "doubles": 36,
      "triples": 4,
      "home_runs": 23,
      "strike_outs": 233,
      "base_on_balls": 77,
      "intentional_walks": 2,
      "hits": 207,
      "hit_by_pitch": 4,
      "avg": 0.239,
      "at_bats": 867,
      "obp": 0.301,
      "slg": 0.369,
      "ops": 0.67,
      "caught_stealing": 5,
      "stolen_bases": 6,
      "stolen_base_percentage": 0.545,
      "ground_into_double_play": 13,
      "number_of_pitches": 3724,
      "plate_appearances": 959,
      "total_bases": 320,
      "rbi": 105,
      "left_on_base": 173,
      "sac_bunts": 3,
      "sac_flies": 8,
      "babip": 0.297,
      "ground_outs_to_airouts": 1.13,
      "at_bats_per_home_run": 37.7
    },
    "pitching_stats": {
      "games_played": 26,
      "games_started": 26,
      "ground_outs": 218,
      "air_outs": 207,
      "runs": 142,
      "doubles": 53,
      "triples": 1,
      "home_runs": 43,
      "strike_outs": 234,
      "base_on_balls": 104,
      "intentional_walks": 1,
      "hits": 213,
      "hit_by_pitch": 16,
      "avg": 0.247,
      "at_bats": 864,
      "era": 5.06,
      "innings_pitched": 226.0,
      "wins": 10,
      "losses": 16,
      "ties": 0,
      "saves": 4,
      "save_opportunities": 7,
      "holds": 13,
      "blown_saves": 3,
      "earned_runs": 127,
      "whip": 1.4,
      "batters_faced": 993,
      "outs": 678,
      "games_pitched": 26,
      "complete_games": 0,
      "shutouts": 1,
      "strikes": 2434,
      "strike_percentage": 0.61,
      "hit_batsmen": 16,
      "balks": 2,
      "wild_pitches": 10,
      "pickoffs": 3,
      "ground_outs_to_airouts": 1.05,
      "win_percentage": 0.385,
      "pitches_per_inning": 17.74,
      "games_finished": 26,
      "strikeout_walk_ratio": 2.25,
      "strikeouts_per_9inn": 9.32,
      "walks_per_9inn": 4.14,
      "hits_per_9inn": 8.48,
      "runs_scored_per_9": 5.65,
      "home_runs_per_9": 1.71,
      "sac_bunts": 1,
      "sac_flies": 7
    },
    "fielding_stats": {
      "games_played": 26,
      "games_started": 26,
      "assists": 231,
      "put_outs": 678,
      "errors": 25,
      "chances": 934,
      "fielding": 0.973,
      "range_factor_per_game": 34.96,
      "range_factor_per_9inn": 36.2,
      "innings": 226.0,
      "games": 26,
      "double_plays": 27,
      "triple_plays": 0,
      "throwing_errors": 14
    }
  },
  "away_team": {
    "team_id": 113,
    "batting_stats": {
      "games_played": 28,
      "ground_outs": 203,
      "air_outs": 233,
      "runs": 109,
      "doubles": 35,
      "triples": 2,
      "home_runs": 46,
      "strike_outs": 237,
      "base_on_balls": 107,
      "intentional_walks": 1,
      "hits": 187,
      "hit_by_pitch": 15,
      "avg": 0.218,
      "at_bats": 856,
      "obp": 0.315,
      "slg": 0.425,
      "ops": 0.74,
      "caught_stealing": 2,
      "stolen_bases": 15,
      "stolen_base_percentage": 0.882,
      "ground_into_double_play": 27,
      "number_of_pitches": 4066,
      "plate_appearances": 983,
      "total_bases": 364,
      "rbi": 107,
      "left_on_base": 176,
      "sac_bunts": 0,
      "sac_flies": 4,
      "babip": 0.244,
      "ground_outs_to_airouts": 0.87,
      "at_bats_per_home_run": 18.61
    },
    "pitching_stats": {
      "games_played": 28,
      "games_started": 28,
      "ground_outs": 204,
      "air_outs": 207,
      "runs": 121,
      "doubles": 35,
      "triples": 3,
      "home_runs": 36,
      "strike_outs": 10,
      "base_on_balls": 110,
      "intentional_walks": 4,
      "hits": 201,
      "hit_by_pitch": 10,
      "avg": 0.231,
      "at_bats": 869,
      "era": 4.27,
      "innings_pitched": 230.0,
      "wins": 13,
      "losses": 15,
      "ties": 0,
      "saves": 4,
      "save_opportunities": 7,
      "holds": 10,
      "blown_saves": 3,
      "earned_runs": 109,
      "whip": 1.35,
      "batters_faced": 998,
      "outs": 690,
      "games_pitched": 28,
      "complete_games": 1,
      "shutouts": 2,
      "strikes": 2511,
      "strike_percentage": 0.61,
      "hit_batsmen": 10,
      "balks": 3,
      "wild_pitches": 10,
      "pickoffs": 0,
      "ground_outs_to_airouts": 0.99,
      "win_percentage": 0.464,
      "pitches_per_inning": 17.96,
      "games_finished": 27,
      "strikeout_walk_ratio": 2.42,
      "strikeouts_per_9inn": 10.41,
      "walks_per_9inn": 4.3,
      "hits_per_9inn": 7.87,
      "runs_scored_per_9": 4.73,
      "home_runs_per_9": 1.41,
      "sac_bunts": 2,
      "sac_flies": 7
    },
    "fielding_stats": {
      "games_played": 28,
      "games_started": 28,
      "assists": 203,
      "put_outs": 690,
      "errors": 15,
      "chances": 908,
      "fielding": 0.983,
      "range_factor_per_game": 31.89,
      "range_factor_per_9inn": 34.94,
      "innings": 230.0,
      "games": 28,
      "double_plays": 20,
      "triple_plays": 0,
      "throwing_errors": 6
    }
  },
  "result": {
    "home_team_score": 3,
    "away_team_score": 2
  }
}