{
  "setting": {
    "date": {
      "year": 2016,
      "month": 9,
      "day": 2
    }
  },
  "home_team": {
    "team_id": 143,
    "batting_stats": {
      "games_played": 26,
      "ground_outs": 235,
      "air_outs": 217,
      "runs": 103,
      "doubles": 39,
      "triples": 4,
      "home_runs": 30,
      "strike_outs": 238,
      "base_on_balls": 71,
      "intentional_walks": 7,
      "hits": 203,
      "hit_by_pitch": 9,
      "avg": 0.23,
      "at_bats": 884,
      "obp": 0.293,
      "slg": 0.385,
      "ops": 0.678,
      "caught_stealing": 5,
      "stolen_bases": 16,
      "stolen_base_percentage": 0.762,
      "ground_into_double_play": 20,
      "number_of_pitches": 3866,
      "plate_appearances": 973,
      "total_bases": 340,
      "rbi": 97,
      "left_on_base": 166,
      "sac_bunts": 6,
      "sac_flies": 3,
      "babip": 0.279,
      "ground_outs_to_airouts": 1.08,
      "at_bats_per_home_run": 29.47
    },
    "pitching_stats": {
      "games_played": 26,
      "games_started": 26,
      "ground_outs": 201,
      "air_outs": 13,
      "runs": 152,
      "doubles": 50,
      "triples": 4,
      "home_runs": 50,
      "strike_outs": 211,
      "base_on_balls": 75,
      "intentional_walks": 2,
      "hits": 2,
      "hit_by_pitch": 6,
      "avg": 0.281,
      "at_bats": 919,
      "era": 5.5,
      "innings_pitched": 234.0,
      "wins": 11,
      "losses": 15,
      "ties": 0,
      "saves": 7,
      "save_opportunities": 8,
      "holds": 17,
      "blown_saves": 1,
      "earned_runs": 143,
      "whip": 1.42,
      "batters_faced": 1020,
      "outs": 702,
      "games_pitched": 26,
      "complete_games": 0,
      "shutouts": 0,
      "strikes": 2510,
      "strike_percentage": 0.62,
      "hit_batsmen": 6,
      "balks": 2,
      "wild_pitches": 8,
      "pickoffs": 1,
      "ground_outs_to_airouts": 0.75,
      "win_percentage": 0.423,
      "pitches_per_inning": 17.17,
      "games_finished": 26,
      "strikeout_walk_ratio": 2.81,
      "strikeouts_per_9inn": 8.12,
      "walks_per_9inn": 2.88,
      "hits_per_9inn": 9.92,
      "runs_scored_per_9": 5.85,
      "home_runs_per_9": 1.92,
      "sac_bunts": 9,
      "sac_flies": 11
    },
    "fielding_stats": {
      "games_played": 26,
      "games_started": 26,
      "assists": 210,
      "put_outs": 702,
      "errors": 8,
      "chances": 920,
      "fielding": 0.991,
      "range_factor_per_game": 35.08,
      "range_factor_per_9inn": 35.08,
      "innings": 234.0,
      "games": 26,
      "double_plays": 21,
      "triple_plays": 1,
      "throwing_errors": 3
    }
  },
  "away_team": {
    "team_id": 144,
    "batting_stats": {
      "games_played": 29,
      "ground_outs": 48,
      "air_outs": 235,
      "runs": 154,
      "doubles": 66,
      "triples": 5,
      "home_runs": 28,
      "strike_outs": 209,
      "base_on_balls": 116,
      "intentional_walks": 13,
      "hits": 16,
      "hit_by_pitch": 8,
      "avg": 0.273,
      "at_bats": 996,
      "obp": 0.349,
      "slg": 0.434,
      "ops": 0.783,
      "caught_stealing": 7,
      "stolen_bases": 9,
      "stolen_base_percentage": 0.563,
      "ground_into_double_play": 35,
      "number_of_pitches": 4360,
      "plate_appearances": 1145,
      "total_bases": 432,
      "rbi": 147,
      "left_on_base": 206,
      "sac_bunts": 9,
      "sac_flies": 15,
      "babip": 0.315,
      "ground_outs_to_airouts": 1.29,
      "at_bats_per_home_run": 35.57
    },
    "pitching_stats": {
      "games_played": 29,
      "games_started": 29,
      "ground_outs": 43,
      "air_outs": 236,
      "runs": 160,
      "doubles": 51,
      "triples": 15,
      "home_runs": 36,
      "strike_outs": 221,
      "base_on_balls": 96,
      "intentional_walks": 4,
      "hits": 11,
      "hit_by_pitch": 12,
      "avg": 0.266,
      "at_bats": 1003,
      "era": 5.18,
      "innings_pitched": 258.2,
      "wins": 15,
      "losses": 14,
      "ties": 0,
      "saves": 9,
      "save_opportunities": 10,
      "holds": 12,
      "blown_saves": 1,
      "earned_runs": 149,
      "whip": 1.4,
      "batters_faced": 1131,
      "outs": 776,
      "games_pitched": 29,
      "complete_games": 0,
      "shutouts": 0,
      "strikes": 2807,
      "strike_percentage": 0.63,
      "hit_batsmen": 12,
      "balks": 0,
      "wild_pitches": 17,
      "pickoffs": 0,
      "ground_outs_to_airouts": 1.27,
      "win_percentage": 0.517,
      "pitches_per_inning": 17.26,
      "games_finished": 29,
      "strikeout_walk_ratio": 2.3,
      "strikeouts_per_9inn": 7.69,
      "walks_per_9inn": 3.34,
      "hits_per_9inn": 9.29,
      "runs_scored_per_9": 5.57,
      "home_runs_per_9": 1.25,
      "sac_bunts": 8,
      "sac_flies": 12
    },
    "fielding_stats": {
      "games_played": 29,
      "games_started": 29,
      "assists": 297,
      "put_outs": 776,
      "errors": 16,
      "chances": 1089,
      "fielding": 0.985,
      "range_factor_per_game": 37.0,
      "range_factor_per_9inn": 37.43,
      "innings": 258.2,
      "games": 29,
      "double_plays": 18,
      "triple_plays": 0,
      "throwing_errors": 8
    }
  },
  "result": {
    "home_team_score": 4,
    "away_team_score": 8
  }
}