{
  "setting": {
    "date": {
      "year": 2016,
      "month": 4,
      "day": 30
    }
  },
  "home_team": {
    "team_id": 143,
    "batting_stats": {
      "games_played": 24,
      "ground_outs": 217,
      "air_outs": 198,
      "runs": 80,
      "doubles": 35,
      "triples": 5,
      "home_runs": 21,
      "strike_outs": 204,
      "base_on_balls": 64,
      "intentional_walks": 6,
      "hits": 181,
      "hit_by_pitch": 6,
      "avg": 0.231,
      "at_bats": 782,
      "obp": 0.292,
      "slg": 0.37,
      "ops": 0.662,
      "caught_stealing": 9,
      "stolen_bases": 10,
      "stolen_base_percentage": 0.526,
      "ground_into_double_play": 18,
      "number_of_pitches": 3391,
      "plate_appearances": 870,
      "total_bases": 289,
      "rbi": 75,
      "left_on_base": 144,
      "sac_bunts": 11,
      "sac_flies": 7,
      "babip": 0.284,
      "ground_outs_to_airouts": 1.1,
      "at_bats_per_home_run": 37.24
    },
    "pitching_stats": {
      "games_played": 24,
      "games_started": 24,
      "ground_outs": 196,
      "air_outs": 197,
      "runs": 97,
      "doubles": 48,
      "triples": 3,
      "home_runs": 29,
      "strike_outs": 245,
      "base_on_balls": 67,
      "intentional_walks": 4,
      "hits": 185,
      "hit_by_pitch": 4,
      "avg": 0.228,
      "at_bats": 810,
      "era": 3.79,
      "innings_pitched": 216.1,
      "wins": 14,
      "losses": 10,
      "ties": 0,
      "saves": 8,
      "save_opportunities": 10,
      "holds": 19,
      "blown_saves": 2,
      "earned_runs": 91,
      "whip": 1.16,
      "batters_faced": 894,
      "outs": 649,
      "games_pitched": 24,
      "complete_games": 1,
      "shutouts": 5,
      "strikes": 2247,
      "strike_percentage": 0.64,
      "hit_batsmen": 4,
      "balks": 1,
      "wild_pitches": 5,
      "pickoffs": 2,
      "ground_outs_to_airouts": 0.99,
      "win_percentage": 0.583,
      "pitches_per_inning": 16.21,
      "games_finished": 23,
      "strikeout_walk_ratio": 3.66,
      "strikeouts_per_9inn": 10.19,
      "walks_per_9inn": 2.79,
      "hits_per_9inn": 7.7,
      "runs_scored_per_9": 4.04,
      "home_runs_per_9": 1.21,
      "sac_bunts": 7,
      "sac_flies": 6
    },
    "fielding_stats": {
      "games_played": 24,
      "games_started": 24,
      "assists": 203,
      "put_outs": 649,
      "errors": 12,
      "chances": 864,
      "fielding": 0.986,
      "range_factor_per_game": 35.5,
      "range_factor_per_9inn": 35.5,
      "innings": 216.1,
      "games": 24,
      "double_plays": 9,
      "triple_plays": 0,
      "throwing_errors": 3
    }
  },
  "away_team": {
    "team_id": 114,
    "batting_stats": {
      "games_played": 21,
      "ground_outs": 170,
      "air_outs": 187,
      "runs": 91,
      "doubles": 40,
      "triples": 4,
      "home_runs": 20,
      "strike_outs": 195,
      "base_on_balls": 62,
      "intentional_walks": 3,
      "hits": 178,
      "hit_by_pitch": 2,
      "avg": 0.248,
      "at_bats": 717,
      "obp": 0.306,
      "slg": 0.399,
      "ops": 0.705,
      "caught_stealing": 5,
      "stolen_bases": 19,
      "stolen_base_percentage": 0.792,
      "ground_into_double_play": 13,
      "number_of_pitches": 3166,
      "plate_appearances": 794,
      "total_bases": 286,
      "rbi": 88,
      "left_on_base": 136,
      "sac_bunts": 3,
      "sac_flies": 10,
      "babip": 0.309,
      "ground_outs_to_airouts": 0.91,
      "at_bats_per_home_run": 35.85
    },
    "pitching_stats": {
      "games_played": 21,
      "games_started": 21,
      "ground_outs": 187,
      "air_outs": 187,
      "runs": 85,
      "doubles": 37,
      "triples": 2,
      "home_runs": 26,
      "strike_outs": 169,
      "base_on_balls": 61,
      "intentional_walks": 6,
      "hits": 162,
      "hit_by_pitch": 6,
      "avg": 0.231,
      "at_bats": 700,
      "era": 4.01,
      "innings_pitched": 186.1,
      "wins": 10,
      "losses": 11,
      "ties": 0,
      "saves": 7,
      "save_opportunities": 9,
      "holds": 10,
      "blown_saves": 2,
      "earned_runs": 83,
      "whip": 1.2,
      "batters_faced": 772,
      "outs": 559,
      "games_pitched": 21,
      "complete_games": 0,
      "shutouts": 1,
      "strikes": 1875,
      "strike_percentage": 0.63,
      "hit_batsmen": 6,
      "balks": 1,
      "wild_pitches": 9,
      "pickoffs": 1,
      "ground_outs_to_airouts": 1.0,
      "win_percentage": 0.476,
      "pitches_per_inning": 16.02,
      "games_finished": 21,
      "strikeout_walk_ratio": 2.77,
      "strikeouts_per_9inn": 8.16,
      "walks_per_9inn": 2.95,
      "hits_per_9inn": 7.82,
      "runs_scored_per_9": 4.11,
      "home_runs_per_9": 1.26,
      "sac_bunts": 2,
      "sac_flies": 3
    },
    "fielding_stats": {
      "games_played": 21,
      "games_started": 21,
      "assists": 193,
      "put_outs": 559,
      "errors": 12,
      "chances": 764,
      "fielding": 0.984,
      "range_factor_per_game": 35.81,
      "range_factor_per_9inn": 36.39,
      "innings": 186.1,
      "games": 21,
      "double_plays": 9,
      "triple_plays": 0,
      "throwing_errors": 5
    }
  },
  "result": {
    "home_team_score": 4,
    "away_team_score": 3
  }
}